{"id": "043a836f-f6d6-4f1a-b0c1-18d68428b666", "display_name": "riffusion/riffusion", "description": null, "short_desc": null, "endpoints": [{"id": "predict_predictions_post", "display_name": "predict_predictions_post", "description": "Run a single prediction on the model", "short_desc": "Predict", "path": "/predictions", "parameters": [{"name": "alpha", "type": "number", "required": false, "default": 0.5, "location": "body", "param_schema": {"type": "number", "title": "Alpha", "default": 0.5, "maximum": 1, "minimum": 0, "x-order": 3, "description": "Interpolation alpha if using two prompts. A value of 0 uses prompt_a fully, a value of 1 uses prompt_b fully"}, "description": "Interpolation alpha if using two prompts. A value of 0 uses prompt_a fully, a value of 1 uses prompt_b fully"}, {"name": "prompt_a", "type": "string", "required": false, "default": "funky synth solo", "location": "body", "param_schema": {"type": "string", "title": "Prompt A", "default": "funky synth solo", "x-order": 0, "description": "The prompt for your audio"}, "description": "The prompt for your audio"}, {"name": "prompt_b", "type": "string", "required": false, "default": null, "location": "body", "param_schema": {"type": "string", "title": "Prompt B", "x-order": 2, "description": "The second prompt to interpolate with the first, leave blank if no interpolation"}, "description": "The second prompt to interpolate with the first, leave blank if no interpolation"}, {"name": "denoising", "type": "number", "required": false, "default": 0.75, "location": "body", "param_schema": {"type": "number", "title": "Denoising", "default": 0.75, "maximum": 1, "minimum": 0, "x-order": 1, "description": "How much to transform input spectrogram"}, "description": "How much to transform input spectrogram"}, {"name": "seed_image_id", "type": "string", "required": false, "default": "vibes", "location": "body", "param_schema": {"allOf": [{"$ref": "#/components/schemas/seed_image_id"}], "default": "vibes", "x-order": 5, "description": "Seed spectrogram to use"}, "description": "Seed spectrogram to use"}, {"name": "num_inference_steps", "type": "integer", "required": false, "default": 50, "location": "body", "param_schema": {"type": "integer", "title": "Num Inference Steps", "default": 50, "minimum": 1, "x-order": 4, "description": "Number of steps to run the diffusion model"}, "description": "Number of steps to run the diffusion model"}], "responses": {"200": {"content": {"application/json": {"schema": {"$ref": "#/components/schemas/PredictionResponse"}}}, "description": "Successful Response"}, "422": {"content": {"application/json": {"schema": {"$ref": "#/components/schemas/HTTPValidationError"}}}, "description": "Validation Error"}}, "timeout_s": null}], "specification": "socaity", "used_models": [], "category": ["03d59d4b-1b52-4f10-a613-fe9cb7511a6d"], "family_id": "17beab39-cce9-4363-b74c-0d61034d7091", "service_address": {"url": "https://api.socaity.ai/v1/riffusion/riffusion"}, "created_at": "2025-06-18T13:00:02.994938+00:00", "version": "9c7a3914b55d8abb5be4c35f78423a32544f340d"}